pyiwsl/__init__.py
pyiwsl/core.py
pyiwsl-0.0.1.dist-info/licenses/LICENSE
pyiwsl-0.0.1.dist-info/METADATA
pyiwsl-0.0.1.dist-info/WHEEL
pyiwsl-0.0.1.dist-info/top_level.txt
pyiwsl-0.0.1.dist-info/RECORD
