Metadata-Version: 2.4
Name: pyiwsl
Version: 0.0.1
Summary: pyiwsl package
Author-email: Duhwan Hwang <naemduu@snu.ac.kr>
License-Expression: MIT AND (Apache-2.0 OR BSD-2-Clause)
Project-URL: Repository, https://github.com/naemduu/pyiwsl
Requires-Python: >=3.9
License-File: LICENSE
Dynamic: license-file
